{
  "64db6b62fd897800013a91b0": {
    "done": true,
    "carousels": 0
  },
  "64db6b88fd897800013a9a4c": {
    "done": true,
    "carousels": 0
  },
  "64db6b6dfd897800013a930e": {
    "done": true,
    "carousels": 0
  },
  "64db6b74fd897800013a9512": {
    "done": true,
    "carousels": 0
  },
  "64db6b7dfd897800013a97bc": {
    "done": true,
    "carousels": 0
  },
  "64db6b82fd897800013a9942": {
    "done": true,
    "carousels": 0
  },
  "64e063fafd8978000123ea12": {
    "done": true,
    "carousels": 0
  },
  "64e35774fd89780001ace043": {
    "done": true,
    "carousels": 0
  },
  "64e730ddfd89780001336a09": {
    "done": true,
    "carousels": 0
  },
  "64e1eb78fd897800017d0ec7": {
    "done": true,
    "carousels": 0
  },
  "64fdaddefd89780001bdb780": {
    "done": true,
    "carousels": 0
  },
  "651b8da8fd89780001974847": {
    "done": true,
    "carousels": 3
  },
  "65348754fd89780001b2a259": {
    "done": true,
    "carousels": 0
  },
  "653914f6fd89780001fef733": {
    "done": true,
    "carousels": 0
  },
  "654249defd89780001041c87": {
    "done": true,
    "carousels": 0
  },
  "6544f321fd89780001bb240c": {
    "done": true,
    "carousels": 0
  },
  "6544370afd89780001e1546c": {
    "done": true,
    "carousels": 0
  },
  "65472977fd89780001cf3ce6": {
    "done": true,
    "carousels": 0
  },
  "654b8438fd897800016bf4cc": {
    "done": true,
    "carousels": 0
  },
  "655a0f5bfd89780001a49e07": {
    "done": true,
    "carousels": 0
  },
  "65a3438afd89780001d93651": {
    "done": true,
    "carousels": 0
  },
  "65a51edbfd89780001ffc7b2": {
    "done": true,
    "carousels": 0
  },
  "65c8e2dffd89780001346aa9": {
    "done": true,
    "carousels": 1
  },
  "65ccaacffd89780001502bc5": {
    "done": true,
    "carousels": 0
  },
  "65d0e089fd89780001320e4c": {
    "done": true,
    "carousels": 0
  },
  "65d21157fd897800013be576": {
    "done": true,
    "carousels": 8
  },
  "65d07704fd897800012d51fe": {
    "done": true,
    "carousels": 0
  },
  "65ed5114fd89780001dcc688": {
    "done": true,
    "carousels": 0
  },
  "65ba3bfefd89780001650f07": {
    "done": true,
    "carousels": 0
  },
  "65f8e4d2fd89780001b5e8f9": {
    "done": true,
    "carousels": 0
  },
  "65fd4f9cfd8978000157e5ff": {
    "done": true,
    "carousels": 0
  },
  "65ff99e2fd897800016c300e": {
    "done": true,
    "carousels": 0
  },
  "65fff19efd897800017026b5": {
    "done": true,
    "carousels": 0
  },
  "6604201efd89780001032e98": {
    "done": true,
    "carousels": 0
  },
  "6608d51bfd89780001256dc5": {
    "done": true,
    "carousels": 0
  },
  "6609003dfd89780001273bee": {
    "done": true,
    "carousels": 0
  },
  "660d4c83fd89780001ddf0ad": {
    "done": true,
    "carousels": 1
  },
  "660e349bfd89780001e40cbc": {
    "done": true,
    "carousels": 0
  },
  "660bcff3fd89780001d037ad": {
    "done": true,
    "carousels": 0
  },
  "661cecd5fd897800019390f6": {
    "done": true,
    "carousels": 0
  },
  "66235080fd8978000137921f": {
    "done": true,
    "carousels": 0
  },
  "660ff581fd89780001f31315": {
    "done": true,
    "carousels": 0
  },
  "6628f08cfd8978000190a575": {
    "done": true,
    "carousels": 20
  },
  "662e156bfd8978000130c73c": {
    "done": true,
    "carousels": 23
  },
  "66337971fd8978000101052f": {
    "done": true,
    "carousels": 0
  },
  "66405077fd89780001f23b72": {
    "done": true,
    "carousels": 0
  },
  "665083f0fd8978000151d7e8": {
    "done": true,
    "carousels": 1
  },
  "6655eceefd897800015c1b6a": {
    "done": true,
    "carousels": 0
  },
  "665c5a03fd89780001224bab": {
    "done": true,
    "carousels": 1
  },
  "666425e6fd8978000121dadc": {
    "done": true,
    "carousels": 1
  },
  "6668f9f5fd89780001e844ca": {
    "done": true,
    "carousels": 0
  },
  "6658817efd89780001222f04": {
    "done": true,
    "carousels": 0
  },
  "6628aadefd897800018ca028": {
    "done": true,
    "carousels": 0
  },
  "66551cfefd897800011f9d5e": {
    "done": true,
    "carousels": 6
  },
  "665f1689fd89780001afd058": {
    "done": true,
    "carousels": 3
  },
  "6698eaf2fd89780001c6d5d9": {
    "done": true,
    "carousels": 0
  },
  "66a4562afd89780001d70329": {
    "done": true,
    "carousels": 16
  },
  "66ac535efd89780001d5363a": {
    "done": true,
    "carousels": 1
  },
  "669262c9fd89780001902a76": {
    "done": true,
    "carousels": 1
  },
  "66b20b15fd89780001ceef6b": {
    "done": true,
    "carousels": 16
  },
  "66b41018fd89780001f96fc3": {
    "done": true,
    "carousels": 0
  },
  "66b5be79fd897800016df66e": {
    "done": true,
    "carousels": 0
  },
  "669c8097fd89780001f355be": {
    "done": true,
    "carousels": 2
  },
  "66bb07a5fd8978000100f7da": {
    "done": true,
    "carousels": 0
  },
  "66a504cbfd89780001e237b8": {
    "done": true,
    "carousels": 0
  },
  "669488eafd89780001cc7d82": {
    "done": true,
    "carousels": 0
  },
  "66c3e440fd897800014425a8": {
    "done": true,
    "carousels": 22
  },
  "66cab3d1fd89780001669923": {
    "done": true,
    "carousels": 0
  },
  "66b715defd89780001b25a1e": {
    "done": true,
    "carousels": 0
  },
  "66db220afd897800013d1c78": {
    "done": true,
    "carousels": 2
  },
  "66c0ba76fd89780001527eed": {
    "done": true,
    "carousels": 2
  },
  "66ee9770fd89780001306753": {
    "done": true,
    "carousels": 9
  },
  "66b9bb70fd89780001e631c6": {
    "done": true,
    "carousels": 0
  },
  "66d4538ffd897800012f025a": {
    "done": true,
    "carousels": 0
  },
  "66e06a8dfd89780001ffbbc3": {
    "done": true,
    "carousels": 1
  },
  "67094049fd8978000167f9f9": {
    "done": true,
    "carousels": 0
  },
  "670fc5b2fd89780001cea7ee": {
    "done": true,
    "carousels": 0
  },
  "66adfb9afd89780001f62df1": {
    "done": true,
    "carousels": 0
  },
  "671f86f1fd89780001de9fae": {
    "done": true,
    "carousels": 0
  },
  "67205cb1fd89780001ee1413": {
    "done": true,
    "carousels": 14
  },
  "6724e866fd897800019382f6": {
    "done": true,
    "carousels": 3
  },
  "67270573fd89780001adf758": {
    "done": true,
    "carousels": 0
  },
  "67239706fd89780001749b01": {
    "done": true,
    "carousels": 0
  },
  "66fcb508fd897800012664ef": {
    "done": true,
    "carousels": 0
  },
  "670688f2fd8978000138a466": {
    "done": true,
    "carousels": 0
  },
  "67375f47fd89780001591deb": {
    "done": true,
    "carousels": 0
  },
  "6718dcb7fd897800013bcb4e": {
    "done": true,
    "carousels": 0
  },
  "673f301bfd89780001681af8": {
    "done": true,
    "carousels": 2
  },
  "67451f5afd89780001f002f2": {
    "done": true,
    "carousels": 10
  },
  "6746742bfd897800018d4906": {
    "done": true,
    "carousels": 0
  },
  "67448c52fd89780001e759ca": {
    "done": true,
    "carousels": 1
  },
  "674bb924fd8978000120ac11": {
    "done": true,
    "carousels": 0
  },
  "67775955fd89780001fec8cc": {
    "done": true,
    "carousels": 0
  },
  "67875dbafd89780001aa4818": {
    "done": true,
    "carousels": 0
  },
  "6789be68fd89780001c3ec93": {
    "done": true,
    "carousels": 0
  },
  "678b1d81fd89780001f7fe4d": {
    "done": true,
    "carousels": 0
  },
  "678cad2cfd89780001326626": {
    "done": true,
    "carousels": 0
  },
  "678cc1c2fd897800013561fe": {
    "done": true,
    "carousels": 0
  },
  "678cd483fd8978000137dedf": {
    "done": true,
    "carousels": 0
  },
  "678ce3f3fd8978000139e3bf": {
    "done": true,
    "carousels": 0
  },
  "678d9408fd89780001529ad2": {
    "done": true,
    "carousels": 0
  },
  "678dada2fd897800015779fb": {
    "done": true,
    "carousels": 0
  },
  "678e30cbfd89780001f72fc6": {
    "done": true,
    "carousels": 0
  },
  "679b6130fd897800011593a6": {
    "done": true,
    "carousels": 0
  },
  "679f6ce7fd89780001f18c4a": {
    "done": true,
    "carousels": 0
  },
  "679ccd73fd897800016e1e52": {
    "done": true,
    "carousels": 0
  },
  "67a813d4fd8978000165ae91": {
    "done": true,
    "carousels": 0
  },
  "679370fefd89780001df01e0": {
    "done": true,
    "carousels": 0
  },
  "679ee4d8fd89780001d625b6": {
    "done": true,
    "carousels": 0
  },
  "67d42835fd897800014ffc83": {
    "done": true,
    "carousels": 0
  },
  "6735d8e7fd897800013ead73": {
    "done": true,
    "carousels": 0
  },
  "671263f0fd89780001ee6da7": {
    "done": true,
    "carousels": 0
  },
  "67f1f8fbfd89780001607840": {
    "done": true,
    "carousels": 2
  },
  "67f76284fd89780001bede9f": {
    "done": true,
    "carousels": 4
  },
  "681601c6fd8978000139f8a3": {
    "done": true,
    "carousels": 0
  },
  "6839ae23fd897800010b9b32": {
    "done": true,
    "carousels": 0
  },
  "683ea036fd89780001ff6ce2": {
    "done": true,
    "carousels": 0
  },
  "64e37f2dfd89780001b1f776": {
    "done": true,
    "carousels": 0
  },
  "685101c0fd89780001e221f4": {
    "done": true,
    "carousels": 0
  },
  "68540320fd8978000126a919": {
    "done": true,
    "carousels": 0
  },
  "685a4e9dfd897800015f493d": {
    "done": true,
    "carousels": 0
  },
  "6863ccb0fd8978000142a65c": {
    "done": true,
    "carousels": 0
  },
  "68734213fd897800016298ef": {
    "done": true,
    "carousels": 0
  },
  "654c6271fd8978000174ff5e": {
    "done": true,
    "carousels": 2
  },
  "687f11d5fd89780001df5032": {
    "done": true,
    "carousels": 0
  },
  "68818eddfd897800017a2dfb": {
    "done": true,
    "carousels": 0
  },
  "6881b9fafd897800011f152f": {
    "done": true,
    "carousels": 0
  },
  "6896f79ffd897800015c59f7": {
    "done": true,
    "carousels": 0
  },
  "660e6e92fd89780001e6047e": {
    "done": true,
    "carousels": 22
  },
  "68b8d2e3fd897800017acaee": {
    "done": true,
    "carousels": 1
  },
  "68d49203fd89780001e4c5ef": {
    "done": true,
    "carousels": 0
  },
  "68e51c8efd897800014e36a6": {
    "done": true,
    "carousels": 2
  },
  "68f45c39fd8978000150fff0": {
    "done": true,
    "carousels": 2
  },
  "690ae7cafd89780001e08158": {
    "done": true,
    "carousels": 1
  },
  "69170335fd89780001bcca63": {
    "done": true,
    "carousels": 2
  },
  "696a37c5fd89780001f0790b": {
    "done": true,
    "carousels": 0
  },
  "696d9b87fd89780001ca2885": {
    "done": true,
    "carousels": 1
  },
  "6970b673fd897800013623d5": {
    "done": true,
    "carousels": 1
  },
  "698d771afd89780001418f97": {
    "done": true,
    "carousels": 0
  },
  "6995d6f6fd89780001575756": {
    "done": true,
    "carousels": 0
  }
}